{
  "config": {
    "configFile": "C:\\SYLVAIN\\PlaywrightTraining\\playwright.config.ts",
    "rootDir": "C:/SYLVAIN/PlaywrightTraining",
    "forbidOnly": false,
    "fullyParallel": false,
    "globalSetup": null,
    "globalTeardown": null,
    "globalTimeout": 0,
    "grep": {},
    "grepInvert": null,
    "maxFailures": 0,
    "metadata": {
      "actualWorkers": 1
    },
    "preserveOutput": "always",
    "reporter": [
      [
        "dot",
        null
      ],
      [
        "json",
        {
          "outputFile": "jsonReports/jesonReport.json"
        }
      ],
      [
        "html",
        {
          "open": "always"
        }
      ]
    ],
    "reportSlowTests": {
      "max": 5,
      "threshold": 300000
    },
    "quiet": false,
    "projects": [
      {
        "outputDir": "C:/SYLVAIN/PlaywrightTraining/test-results",
        "repeatEach": 1,
        "retries": 0,
        "metadata": {
          "actualWorkers": 1
        },
        "id": "",
        "name": "",
        "testDir": "C:/SYLVAIN/PlaywrightTraining",
        "testIgnore": [],
        "testMatch": [
          "**/*.@(spec|test).?(c|m)[jt]s?(x)"
        ],
        "timeout": 30000
      }
    ],
    "shard": null,
    "updateSnapshots": "missing",
    "updateSourceMethod": "3way",
    "version": "1.56.0",
    "workers": 8,
    "webServer": null
  },
  "suites": [
    {
      "title": "tests\\training\\upload.test.ts",
      "file": "tests/training/upload.test.ts",
      "column": 0,
      "line": 0,
      "specs": [
        {
          "title": "File upload with multiple selection verification",
          "ok": true,
          "tags": [],
          "tests": [
            {
              "timeout": 30000,
              "annotations": [],
              "expectedStatus": "passed",
              "projectId": "",
              "projectName": "",
              "results": [
                {
                  "workerIndex": 0,
                  "parallelIndex": 0,
                  "status": "passed",
                  "duration": 1589,
                  "errors": [],
                  "stdout": [
                    {
                      "text": "Multiple selection enabled: true\n"
                    },
                    {
                      "text": "Files selected\n"
                    },
                    {
                      "text": "Files successfully displayed in upload list\n"
                    }
                  ],
                  "stderr": [],
                  "retry": 0,
                  "startTime": "2025-10-24T17:12:33.261Z",
                  "annotations": [],
                  "attachments": [
                    {
                      "name": "screenshot",
                      "contentType": "image/png",
                      "path": "C:\\SYLVAIN\\PlaywrightTraining\\test-results\\tests-training-upload-File-2f646-iple-selection-verification\\test-finished-1.png"
                    },
                    {
                      "name": "video",
                      "contentType": "video/webm",
                      "path": "C:\\SYLVAIN\\PlaywrightTraining\\test-results\\tests-training-upload-File-2f646-iple-selection-verification\\video.webm"
                    }
                  ]
                }
              ],
              "status": "expected"
            }
          ],
          "id": "a41b1f159a469c660911-540965f8431f1c15cc63",
          "file": "tests/training/upload.test.ts",
          "line": 4,
          "column": 5
        }
      ]
    }
  ],
  "errors": [],
  "stats": {
    "startTime": "2025-10-24T17:12:31.221Z",
    "duration": 4171,
    "expected": 1,
    "skipped": 0,
    "unexpected": 0,
    "flaky": 0
  }
}